examples/README.md
examples/embeddings_example.py
examples/example_decorator.py
examples/example_metadata.py
examples/example_simple.py
examples/example_streaming.py
examples/getting_started.py
examples/trace_visualization_example.py
revenium_middleware_ollama/__init__.py
revenium_middleware_ollama/middleware.py
revenium_middleware_ollama/trace_fields.py
revenium_middleware_ollama-0.3.0.dist-info/licenses/LICENSE
revenium_middleware_ollama-0.3.0.dist-info/METADATA
revenium_middleware_ollama-0.3.0.dist-info/WHEEL
revenium_middleware_ollama-0.3.0.dist-info/top_level.txt
revenium_middleware_ollama-0.3.0.dist-info/RECORD
