Metadata-Version: 2.4
Name: revenium-middleware-ollama
Version: 0.3.0
Summary: A Python library that meters Ollama usage to Revenium.
Author-email: Revenium <info@revenium.io>
License: MIT
Project-URL: Homepage, https://github.com/revenium/revenium-middleware-ollama-python
Project-URL: Bug Tracker, https://github.com/revenium/revenium-middleware-ollama-python/issues
Project-URL: Documentation, https://github.com/revenium/revenium-middleware-ollama-python/blob/HEAD/README.md
Keywords: ollama,middleware,logging,token-usage,metering,revenium
Classifier: Development Status :: 4 - Beta
Classifier: Programming Language :: Python :: 3
Classifier: Programming Language :: Python :: 3.8
Classifier: Programming Language :: Python :: 3.9
Classifier: Programming Language :: Python :: 3.10
Classifier: Programming Language :: Python :: 3.11
Classifier: Programming Language :: Python :: 3.12
Classifier: License :: OSI Approved :: MIT License
Classifier: Operating System :: OS Independent
Classifier: Intended Audience :: Developers
Classifier: Topic :: Software Development :: Libraries :: Python Modules
Requires-Python: >=3.8
License-File: LICENSE
Requires-Dist: wrapt
Requires-Dist: ollama
Requires-Dist: revenium_middleware>=0.3.5
Requires-Dist: python-dotenv
Provides-Extra: dev
Requires-Dist: pytest>=7.0.0; extra == "dev"
Requires-Dist: pytest-cov; extra == "dev"
Requires-Dist: flake8; extra == "dev"
Requires-Dist: black; extra == "dev"
Requires-Dist: mypy; extra == "dev"
Requires-Dist: freezegun; extra == "dev"
Dynamic: license-file
